LICENSE
MANIFEST.in
README.md
lgpl-3.0.txt
setup.cfg
setup.py
versioneer.py
python/kabaret/__init__.py
python/kabaret/pyscript_editor.py
python/kabaret/pyscript_flow.py
python/kabaret.script_view.egg-info/PKG-INFO
python/kabaret.script_view.egg-info/SOURCES.txt
python/kabaret.script_view.egg-info/dependency_links.txt
python/kabaret.script_view.egg-info/requires.txt
python/kabaret.script_view.egg-info/top_level.txt
python/kabaret/script_view/__init__.py
python/kabaret/script_view/_version.py
python/kabaret/script_view/debugarea.py
python/kabaret/script_view/linenumberarea.py
python/kabaret/script_view/pythoneditor.py
python/kabaret/script_view/script_view.py
python/kabaret/script_view/script_view_plugin.py
python/kabaret/script_view/syntax.py
python/kabaret/script_view/syntaxstyles.py
python/kabaret/script_view/test.py