Metadata-Version: 2.4
Name: kabaret.script_view
Version: 1.3.1
Summary: Script view extension for the Kabaret framework
Home-page: https://gitlab.com/kabaretstudio/kabaret.script_view
Author: Damien "dee" Coureau
Author-email: kabaret-dev@googlegroups.com
License: LGPLv3+
Keywords: kabaret vfx animation pipeline dataflow workflow asset manager
Classifier: Development Status :: 5 - Production/Stable
Classifier: Topic :: System :: Shells
Classifier: Intended Audience :: Developers
Classifier: Intended Audience :: End Users/Desktop
Classifier: Operating System :: OS Independent
Classifier: Programming Language :: Python :: 3.3
Classifier: License :: OSI Approved :: GNU Lesser General Public License v3 or later (LGPLv3+)
Requires-Python: >=3.3
License-File: LICENSE
Requires-Dist: kabaret>=2.4.0rc6
Provides-Extra: dev
Requires-Dist: twine; extra == "dev"
Requires-Dist: flake8; extra == "dev"
Requires-Dist: black; extra == "dev"
Dynamic: author
Dynamic: author-email
Dynamic: classifier
Dynamic: description
Dynamic: description-content-type
Dynamic: home-page
Dynamic: keywords
Dynamic: license
Dynamic: license-file
Dynamic: provides-extra
Dynamic: requires-dist
Dynamic: requires-python
Dynamic: summary
